napari_unicell/__init__.py
napari_unicell/_widget.py
napari_unicell/napari.yaml
napari_unicell/_tests/__init__.py
napari_unicell/_tests/test_widget.py
napari_unicell/models/__init__.py
napari_unicell/models/unicell_modules.py
napari_unicell/utils/__init__.py
napari_unicell/utils/measures.py
napari_unicell/utils/multi_task_sliding_window_inference.py
napari_unicell/utils/postprocess.py
napari_unicell-0.0.1.post3.dist-info/LICENSE
napari_unicell-0.0.1.post3.dist-info/METADATA
napari_unicell-0.0.1.post3.dist-info/WHEEL
napari_unicell-0.0.1.post3.dist-info/entry_points.txt
napari_unicell-0.0.1.post3.dist-info/top_level.txt
napari_unicell-0.0.1.post3.dist-info/RECORD
