Metadata-Version: 2.1
Name: napari-unicell
Version: 0.0.1.post3
Summary: universal cell segmentation models
Home-page: https://github.com/JunMa11/napari-unicell
Author: Jun Ma
Author-email: junma.ma@mail.utoronto.ca
License: Apache-2.0
Project-URL: Bug Tracker, https://github.com/JunMa11/napari-unicell/issues
Project-URL: Documentation, https://github.com/JunMa11/napari-unicell#README.md
Project-URL: Source Code, https://github.com/JunMa11/napari-unicell
Project-URL: User Support, https://github.com/JunMa11/napari-unicell/issues
Classifier: Development Status :: 2 - Pre-Alpha
Classifier: Framework :: napari
Classifier: Intended Audience :: Developers
Classifier: License :: OSI Approved :: Apache Software License
Classifier: Operating System :: OS Independent
Classifier: Programming Language :: Python
Classifier: Programming Language :: Python :: 3
Classifier: Programming Language :: Python :: 3 :: Only
Classifier: Programming Language :: Python :: 3.8
Classifier: Programming Language :: Python :: 3.9
Classifier: Programming Language :: Python :: 3.10
Classifier: Topic :: Scientific/Engineering :: Image Processing
Requires-Python: >=3.8
License-File: LICENSE
Requires-Dist: torch
Requires-Dist: imagecodecs
Requires-Dist: scipy
Requires-Dist: numpy
Requires-Dist: magicgui
Requires-Dist: qtpy
Requires-Dist: scikit-image
Requires-Dist: monai
Requires-Dist: einops
Requires-Dist: PyQt5
Requires-Dist: napari
Requires-Dist: napari-plugin-engine
Provides-Extra: testing
Requires-Dist: tox ; extra == 'testing'
Requires-Dist: pytest ; extra == 'testing'
Requires-Dist: pytest-cov ; extra == 'testing'
Requires-Dist: pytest-qt ; extra == 'testing'
Requires-Dist: napari ; extra == 'testing'
Requires-Dist: pyqt5 ; extra == 'testing'
